soorma/__init__.py
soorma/agents/__init__.py
soorma/agents/base.py
soorma/agents/planner.py
soorma/agents/tool.py
soorma/agents/worker.py
soorma/ai/event_toolkit.py
soorma/ai/tools.py
soorma/cli/__init__.py
soorma/cli/commands/__init__.py
soorma/cli/commands/dev.py
soorma/cli/commands/init.py
soorma/cli/main.py
soorma/context.py
soorma/events.py
soorma/memory/__init__.py
soorma/memory/client.py
soorma/models.py
soorma/registry/client.py
soorma/utils/schema_utils.py
soorma/workflow.py
soorma_core-0.7.5.dist-info/METADATA
soorma_core-0.7.5.dist-info/WHEEL
soorma_core-0.7.5.dist-info/entry_points.txt
soorma_core-0.7.5.dist-info/licenses/LICENSE.txt
soorma_core-0.7.5.dist-info/RECORD
