Metadata-Version: 2.4
Name: soorma-core
Version: 0.7.5
Summary: The Open Source Foundation for AI Agents. Powered by the DisCo (Distributed Cognition) architecture.
License: MIT
License-File: LICENSE.txt
Keywords: ai,agents,disco,distributed-systems,llm,orchestration
Author: Soorma AI
Author-email: founders@soorma.ai
Requires-Python: >=3.11,<4.0
Classifier: Development Status :: 2 - Pre-Alpha
Classifier: Intended Audience :: Developers
Classifier: License :: OSI Approved :: MIT License
Classifier: Programming Language :: Python :: 3
Classifier: Programming Language :: Python :: 3.11
Classifier: Programming Language :: Python :: 3.12
Classifier: Programming Language :: Python :: 3.13
Classifier: Programming Language :: Python :: 3.14
Classifier: Topic :: Software Development :: Libraries :: Application Frameworks
Requires-Dist: httpx (>=0.26.0)
Requires-Dist: pydantic (>=2.0.0,<3.0.0)
Requires-Dist: rich (>=10.11.0)
Requires-Dist: soorma-common (>=0.7.0)
Requires-Dist: typer (>=0.13.0)
Project-URL: Homepage, https://soorma.ai
Project-URL: Repository, https://github.com/soorma-ai/soorma-core
